verilog code/VerilogDM-212-221.v
/*
STRUCTURAL MODEL VERILOG CODE
------------------------------------
											
WEIGHTED ROUND ROBIN ARBITER 
												
-----------------------------------------------
Mini-Project: CO202 - Design Of Digital Systems
-----------------------------------------------
Reg:       	
GOVIND JEEVAN       16CO221
BIDYADHAR MOHANTY   16CO212
-----------------------------------------------

ABSTRACT:
---------
An arbiter is a device that determines how a common resource is shared amongst mutiple requesters.
The common resource may be a shared memory, a networking switch fabric, or a complex computational element. 

The Weighted Round-Robin (WRR) CPU Scheduling algorithm is based on the round-robin and priority scheduling algorithms.
The WRR allocates the resource for each of the enabled requests for a specific period of time, in order, going back to the 
first served request when all the requests have been granted once.

FUNCTIONALITIES:
----------------
• Accepts request vectors as input. The active requesters are denoted by 1s and inactive requesters by 0s.

• Produces a grant vector as output. Each grant vector has only a single 1, in one clock cycle denoting the granted request.

• Vector Order Arbitration. The arbiter follows 0th to 7th order, granting active requests as it moves.

• Wrap around, At the end of the requests vector, WRR it will return to the requestors at the beginning without losing cycles.

• Work Efficient. WRR skips 0 weighted requesters to serve the next requester with wieight 1. 
  Thus no time slot is wasted on inactive requestors.

BRIEF CODE DESCRIPTION:
----------------

Index Service:
The 8 bits of Request Vector, acts as select lines for 8, 2-1 MUXs with the high input line as the correspoding 3 bit index.
The MUXs corresponding to inactive requests, outputs the value of the preceeding active index.

Grant Service:
An 8-1 Main MUX selects from the 8 different MUX outputs with index values, based on the select line provided by a full adder.
The Full Adder, increments the last granted Index Value by one, and directs the MUX to select the next active index line.

A 2-1 MUX, selects between the output of the Main MUX and the value stored in the register (from previous cycle) depending on
whether any request is active or not.
The Register value is feedbacked to the register itself by the MUX, if no requests are active.

A 3-8 Decoder, decodes the 3 bit index line, to a Grant Vector of 8 bits, that denotes the granted index by a high bit.
*/


module VerilogDM_212_221(request,grant,clk,enable);

	input clk;					// Clock Pulse for sequential elements
	input enable;				// Enable line
	input [7:0] request;		// Request Vector, atmost 8 requesters at a time
	output [7:0] grant; 		// Grant Vector, with 8 possible grants, atmost one at a time

	wire [7:0] out;

	// 3 Bit Index Wires ( 0 -> 7 )
	wire [2:0] ind0;
	wire [2:0] ind1;
	wire [2:0] ind2;
	wire [2:0] ind3;
	wire [2:0] ind4;
	wire [2:0] ind5;
	wire [2:0] ind6;
	wire [2:0] ind7;

	wire [2:0] main_mux_out; // 3 Bit Index Wire selected by MUX in WRR Fashion
	wire [2:0] reg_out;		 // Register Wire with stored index
	wire [2:0] last_mux_out; // 3 Bit Final Granted Index Wire
	wire  [2:0] sel_main;	 // Last Granted Index + 1
	wire any_r;				 // Any Active Requests

	// High, if any one request is active
	assign any_r=request[0]|request[1]|request[2]|request[3]|request[4]|request[5]|request[6]|request[7];

/* 
--------------------------------------------------------------------------------------------------
 INDEX SERVICE
--------------------------------------------------------------------------------------------------
A combinational circuit of 8, 2-1 MUXs.

Data_in_1: 		3 Bit number, denoting the index of the mux. eg ( 010, for Index 2 MUX ) 
Data_in_0: 		Output from the preceeding MUX (in descending order) 
	       		or the output from last MUX in case of first MUX. ( Thus implementing ROUND ROBIN Algorithm )
sel:			Select Line, The bit corresponding to the Index of the MUX in the request vector.
Data_out:		If corresponding request is active, MUX output is the 3 bit INDEX of the MUX. If inactive, it outputs the
				preceeding active request index.

*/


mux2to1 i7(					//2-1 MUX with INDEX 7
	.Data_in_0(ind0),
	.Data_in_1(3'b111),
	.sel(request[7]),
	.Data_out(ind7)
);
mux2to1 i6(					//2-1 MUX with INDEX 6
	.Data_in_0(ind7),
	.Data_in_1(3'b110),
	.sel(request[6]),
	.Data_out(ind6)
);

mux2to1 i5(					//2-1 MUX with INDEX 5
	.Data_in_0(ind6),
	.Data_in_1(3'b101),
	.sel(request[5]),
	.Data_out(ind5)
);

mux2to1 i4(					//2-1 MUX with INDEX 4
	.Data_in_0(ind5),
	.Data_in_1(3'b100),
	.sel(request[4]),
	.Data_out(ind4)
);

mux2to1 i3(					//2-1 MUX with INDEX 3
	.Data_in_0(ind4),
	.Data_in_1(3'b011),
	.sel(request[3]),
	.Data_out(ind3)
);

mux2to1 i2(					//2-1 MUX with INDEX 2
	.Data_in_0(ind3),
	.Data_in_1(3'b010),
	.sel(request[2]),
	.Data_out(ind2)
);

mux2to1 i1(					//2-1 MUX with INDEX 1
	.Data_in_0(ind2),
	.Data_in_1(3'b001),
	.sel(request[1]),
	.Data_out(ind1)
);
mux2to1 i0(					//2-1 MUX with INDEX 0
	.Data_in_0(ind1),
	.Data_in_1(3'b000),
	.sel(request[0]),
	.Data_out(ind0)
);



/* 
--------------------------------------------------------------------------------------------------
 GRANT SERVICE
--------------------------------------------------------------------------------------------------
Implements the round robin arbitration scheme on the 8, 3 bit data lines representing each requester.
A full adder provides the selection line to the main mux, which selects the next input representing
a requester with weight 1.

The output of the Main Mux is feedbacked to the full adder, so that in the event that a line was skipped,
the adder would output the active index succeeding the last selected line, rather than just incrementing by one
which might result in the recently selected line being selected again.

The MUX output is stored in a 3 Bit PIPO register, such that the value is retained until the next clock cycle.

*/


/*
 Main MUX
 --------
 Selects an indexed data line depending on the full adder output
 8, 3 bit lines from the Index servie as 8 Inputs
*/
mux8to1 main_mux1(
	.Data_in_0(ind0),	
	.Data_in_1(ind1),
	.Data_in_2(ind2),
	.Data_in_3(ind3),
	.Data_in_4(ind4),
	.Data_in_5(ind5),
	.Data_in_6(ind6),
	.Data_in_7(ind7),
	.sel(sel_main),		// FULL Adder output
	.clk(clk),
	.Data_out(main_mux_out)
);



/*
 Last MUX (Final Granted Index Line)
 -----------------------------------
 Data_in_0:		If no request is active, it outputs the last granted request, whose value is 
 				stored in the register, from the preceeding clock cycle.
 Data_in_1:		If any of the requests is active, it outputs the currently granted request 
*/
mux2to1 lastmux(
	.Data_in_0(reg_out), 		// Output of the Register
	.Data_in_1(main_mux_out),   // Output of the Main MUX
	.sel(any_r),				// If any request is active
	.Data_out(last_mux_out)		
);



/*
 3-BIT REGISTER
 --------------
 Stores the currently granted request value, as outputed by the lastmux.
 If no requests are active, the register gives the stored value as input to the lastmux, which transfers
 the same into the register in the next clock cycle.

 Retains the last granted request over clock cycles through feedback mechanism.
*/
register bitshiftreg(
	.D(last_mux_out),
	.clk(clk),
	.enable(enable),
	.Q(reg_out)			// Given as feedback to the lastmux and as input to the decoder.
	
);



/*
 FULL ADDER
 ----------
 Increments the last granted request index by one.
 Skips counting the numbers correspnding to the Indexes that was skipped by the Grant MUX.
 Three bit output, Overflow bit is ignored. Cycles from 000 -> 111. 
*/
adder add(
	.inp1(reg_out),		// Value of the last granted request stored by the register
	.inp2(3'b001),		// Incrementing by 1
	.sum(sel_main)		// Selection line to the Main MUX in Grant service
);



/*
 3-8 DECODER
 -----------
 Decodes the three bit index line that was selected by the Grant service, to give an 8 bit number
 The 8 bit output is treated as the GRANT Vector, with a single 1, that corresponds to the index that was granted.
*/
decoder d1(
	
	.x(last_mux_out[2]),
	.y(last_mux_out[1]),
	.z(last_mux_out[0]),
	.d(grant)
);

endmodule

//_______________________________________________________________________________________________________________________

/*
 -----------------
 COMPONENT MODULES 
 -----------------
*/

// FULL ADDER [3 bit]
module adder( inp1 ,inp2 ,sum  );
	output reg [2:0] sum ;
	input [2:0] inp1 ;
	input [2:0] inp2 ; 
	wire [2:0] s;
	wire carry;
	always@(*)
		begin 
			if(inp1!=3'b111)
				
				sum=inp1+inp2;
			else
				sum=3'b000;
		end
endmodule

// 3-BIT PIPO Register
module register(input [2:0] D, input clk, input enable, output reg [2:0] Q); 
   always @(posedge clk) 
	begin 
		if (enable) 
		begin 
			Q <= D; 
		end 
		else Q <= 3'b000;
	end
endmodule


// 2-1 MUX [3 bit]
module mux2to1(
	Data_in_0,
	Data_in_1,
	sel,
	Data_out
	);
	input [2:0] Data_in_0;
	input [2:0] Data_in_1;
	input sel;
	output [2:0] Data_out;
	reg Data_out;
	always @(Data_in_0,Data_in_1,sel)
		begin
			if(sel == 0) 
				Data_out = Data_in_0;   
			else
				Data_out = Data_in_1;   
		end
endmodule

// 3-8 DECODER
module decoder(x,y,z,d);
	output [7:0]d;
	input x,y,z;
	assign d[0] = ~x & ~y & ~z;
	assign d[1] = ~x & ~y & z;
	assign d[2] = ~x & y & ~z;
	assign d[3] = ~x & y & z;
	assign d[4] =  x & ~y & ~z;
	assign d[5] =  x & ~y & z;
	assign d[6] =  x & y & ~z;
	assign d[7] =  x & y & z;
endmodule

// 8-1 MUX [3 bit]
module mux8to1(
		Data_in_0,
		Data_in_1,
		Data_in_2,
		Data_in_3,
		Data_in_4,
		Data_in_5,
		Data_in_6,
		Data_in_7,
		sel,
		clk,
		Data_out
		);
	input [2:0] Data_in_0;
	input [2:0] Data_in_1;
	input [2:0] Data_in_2;
	input [2:0] Data_in_3;
	input [2:0] Data_in_4;
	input [2:0] Data_in_5;
	input [2:0] Data_in_6;
	input [2:0] Data_in_7;
	input [2:0] sel;
	input clk;
	output [2:0] Data_out;
	reg Data_out;
	always @(sel)
		begin
			case (sel) 
				3'b000 : Data_out = Data_in_0; 
				3'b001 : Data_out = Data_in_1; 
				3'b010 : Data_out = Data_in_2; 
				3'b011 : Data_out = Data_in_3; 
				3'b100 : Data_out = Data_in_4; 
				3'b101 : Data_out = Data_in_5; 
				3'b110 : Data_out = Data_in_6; 
				3'b111 : Data_out = Data_in_7; 

				default : Data_out = 8'b00000000; 
			endcase  
		end
		
endmodule

//***************************************************************************************************

verilog code/Verilogt-212-221.v
/*
TESTBENCH
----------------------------------
WEIGHTED ROUND ROBIN ARBITER 				
-----------------------------------------------
Mini-Project: CO202 - Design Of Digital Systems
-----------------------------------------------
Reg:       	
GOVIND JEEVAN       16CO221
BIDYADHAR MOHANTY   16CO212
-----------------------------------------------
ABSTRACT:
---------
An arbiter is a device that determines how a common resource is shared amongst mutiple requesters.
The common resource may be a shared memory, a networking switch fabric, or a complex computational element. 

The Weighted Round-Robin (WRR) CPU Scheduling algorithm is based on the round-robin and priority scheduling algorithms.
The WRR allocates the resource for each of the enabled requests for a specific period of time, in order, going back to the 
first served request when all the requests have been granted once.

FUNCTIONALITIES:
----------------
• Accepts request vectors as input. The active requesters are denoted by 1s and inactive requesters by 0s.

• Produces a grant vector as output. Each grant vector has only a single 1, in one clock cycle denoting the granted request.

• Vector Order Arbitration. The arbiter follows 0th to 7th order, granting active requests as it moves.

• Wrap around, At the end of the requests vector, WRR it will return to the requestors at the beginning without losing cycles.

• Work Efficient. WRR skips 0 weighted requesters to serve the next requester with wieight 1. 
  Thus no time slot is wasted on inactive requestors.
BRIEF CODE DESCRIPTION:
-----------------------
	Common test bench for both behavioral and dataflow modelled arbiter modules. Outputs are displated into the terminal and also
	can be observed by opening the dumpfiles in gtkwave.
*/

module Verilog_212_221();	//TEST MODULE
	reg [7:0] request;		// REQUEST VECTOR. HIGHs INDICATE ACTIVE REQUESTS
	reg enable,clk;			// GRANT VECTOR. HIGH INDICATE THE GRANTED VECTOR
	wire [7:0] grant;

	//VerilogBM_212_221 Verilog_212_221(request,grant,clk,enable);			//UNCOMMENT FOR BEHAVIORAL TESTING
	VerilogDM_212_221 Verilog_212_221(request,grant,clk,enable);			//UNCOMMENT FOR DATAFLOW TESTING
	initial
		begin
			$dumpfile("project.vcd");
			$dumpvars(0,Verilog_212_221);
			clk = 1'b1;			//CLOCK IS INITIALLY HIG
			repeat (100)		//CLOCK PULSE IS CHANGED 100 TIMES AT AN INTERVAL OF 10s
			#10 clk = ~clk;
			
		end
	initial
		begin
			enable=0;
			
			// CIRCUIT IS ENABLED.
			#20;
			enable=1;
			
			// ACTIVE REQUESTS BY 1 and 5
			request=8'b10001000;
			#200;

			// CHANGING THE REQUESTERS
			enable=0;
			#20;
			enable=1;
			request=8'b11100111;
			#200;

			// CHANGING THE REQUESTERS
			enable=0;
			#20;
			enable=1;
			request=8'b00001000;
			#200;

			// CHANGING THE REQUESTERS
			enable=0;
			#20;
			enable=1;
			request=8'b00100010;
			#200;
		end
	initial
		#1000	//TESTBENCH RUNS FOR 1000s
		$finish;

	always@(request)
		$monitor("\n\tREQUEST VECTOR: %b\tGRANT VECTOR: %b\n",request,grant );	//DISPLAYING THE ARBITRATION RESULT FOR EACH NEW GRANT
endmodule

verilog code/VerilogDM-212-221.vcd
$date
	Tue Nov  7 21:08:44 2017
$end
$version
	Icarus Verilog
$end
$timescale
	1s
$end
$scope module Verilog_212_221 $end
$scope module Verilog_212_221 $end
$var wire 1 ! any_r $end
$var wire 1 " clk $end
$var wire 1 # enable $end
$var wire 8 $ request [7:0] $end
$var wire 3 % sel_main [2:0] $end
$var wire 3 & reg_out [2:0] $end
$var wire 3 ' main_mux_out [2:0] $end
$var wire 3 ( last_mux_out [2:0] $end
$var wire 3 ) ind7 [2:0] $end
$var wire 3 * ind6 [2:0] $end
$var wire 3 + ind5 [2:0] $end
$var wire 3 , ind4 [2:0] $end
$var wire 3 - ind3 [2:0] $end
$var wire 3 . ind2 [2:0] $end
$var wire 3 / ind1 [2:0] $end
$var wire 3 0 ind0 [2:0] $end
$var wire 8 1 grant [7:0] $end
$scope module add $end
$var wire 3 2 inp2 [2:0] $end
$var wire 3 3 inp1 [2:0] $end
$var reg 3 4 sum [2:0] $end
$upscope $end
$scope module bitshiftreg $end
$var wire 1 " clk $end
$var wire 1 # enable $end
$var wire 3 5 D [2:0] $end
$var reg 3 6 Q [2:0] $end
$upscope $end
$scope module d1 $end
$var wire 1 7 x $end
$var wire 1 8 y $end
$var wire 1 9 z $end
$var wire 8 : d [7:0] $end
$upscope $end
$scope module i0 $end
$var wire 3 ; Data_in_1 [2:0] $end
$var wire 1 < sel $end
$var wire 3 = Data_in_0 [2:0] $end
$var reg 3 > Data_out [2:0] $end
$upscope $end
$scope module i1 $end
$var wire 3 ? Data_in_1 [2:0] $end
$var wire 1 @ sel $end
$var wire 3 A Data_in_0 [2:0] $end
$var reg 3 B Data_out [2:0] $end
$upscope $end
$scope module i2 $end
$var wire 3 C Data_in_1 [2:0] $end
$var wire 1 D sel $end
$var wire 3 E Data_in_0 [2:0] $end
$var reg 3 F Data_out [2:0] $end
$upscope $end
$scope module i3 $end
$var wire 3 G Data_in_1 [2:0] $end
$var wire 1 H sel $end
$var wire 3 I Data_in_0 [2:0] $end
$var reg 3 J Data_out [2:0] $end
$upscope $end
$scope module i4 $end
$var wire 3 K Data_in_1 [2:0] $end
$var wire 1 L sel $end
$var wire 3 M Data_in_0 [2:0] $end
$var reg 3 N Data_out [2:0] $end
$upscope $end
$scope module i5 $end
$var wire 3 O Data_in_1 [2:0] $end
$var wire 1 P sel $end
$var wire 3 Q Data_in_0 [2:0] $end
$var reg 3 R Data_out [2:0] $end
$upscope $end
$scope module i6 $end
$var wire 3 S Data_in_1 [2:0] $end
$var wire 1 T sel $end
$var wire 3 U Data_in_0 [2:0] $end
$var reg 3 V Data_out [2:0] $end
$upscope $end
$scope module i7 $end
$var wire 3 W Data_in_0 [2:0] $end
$var wire 3 X Data_in_1 [2:0] $end
$var wire 1 Y sel $end
$var reg 3 Z Data_out [2:0] $end
$upscope $end
$scope module lastmux $end
$var wire 3 [ Data_in_0 [2:0] $end
$var wire 1 ! sel $end
$var wire 3 \ Data_in_1 [2:0] $end
$var reg 3 ] Data_out [2:0] $end
$upscope $end
$scope module main_mux1 $end
$var wire 3 ^ Data_in_0 [2:0] $end
$var wire 3 _ Data_in_1 [2:0] $end
$var wire 3 ` Data_in_2 [2:0] $end
$var wire 3 a Data_in_3 [2:0] $end
$var wire 3 b Data_in_4 [2:0] $end
$var wire 3 c Data_in_5 [2:0] $end
$var wire 3 d Data_in_6 [2:0] $end
$var wire 3 e Data_in_7 [2:0] $end
$var wire 1 " clk $end
$var wire 3 f sel [2:0] $end
$var reg 3 g Data_out [2:0] $end
$upscope $end
$upscope $end
$upscope $end
$enddefinitions $end
#0
$dumpvars
b1 g
b1 f
b111 e
b110 d
b101 c
b100 b
b11 a
b10 `
b1 _
b0 ^
b1 ]
b1 \
b0 [
b111 Z
xY
b111 X
b0 W
b110 V
b111 U
xT
b110 S
b101 R
b110 Q
xP
b101 O
b100 N
b101 M
xL
b100 K
b11 J
b100 I
xH
b11 G
b10 F
b11 E
xD
b10 C
b1 B
b10 A
x@
b1 ?
b0 >
b1 =
x<
b0 ;
b10 :
19
08
07
b0 6
b1 5
b1 4
b0 3
b1 2
b10 1
b0 0
b1 /
b10 .
b11 -
b100 ,
b101 +
b110 *
b111 )
b1 (
b1 '
b0 &
b1 %
bx $
0#
1"
x!
$end
#10
0"
#20
b1000 1
b1000 :
18
b11 (
b11 5
b11 ]
b11 '
b11 \
b11 g
b10 %
b10 4
b10 f
b1 &
b1 3
b1 6
b1 [
1!
b111 *
b111 Q
b111 V
b111 d
b111 +
b111 M
b111 R
b111 c
b111 ,
b111 I
b111 N
b111 b
b11 .
b11 A
b11 F
b11 `
b11 /
b11 =
b11 B
b11 _
b11 0
b11 >
b11 W
b11 ^
1Y
0T
0P
0L
1H
0D
0@
0<
1"
b10001000 $
1#
#30
0"
#40
b10000000 1
b10000000 :
17
b111 (
b111 5
b111 ]
b111 '
b111 \
b111 g
b100 %
b100 4
b100 f
b11 &
b11 3
b11 6
b11 [
1"
#50
0"
#60
b1000 1
b1000 :
07
b11 (
b11 5
b11 ]
b11 '
b11 \
b11 g
b0 %
b0 4
b0 f
b111 &
b111 3
b111 6
b111 [
1"
#70
0"
#80
b10000000 1
b10000000 :
17
b111 (
b111 5
b111 ]
b111 '
b111 \
b111 g
b100 %
b100 4
b100 f
b11 &
b11 3
b11 6
b11 [
1"
#90
0"
#100
b1000 1
b1000 :
07
b11 (
b11 5
b11 ]
b11 '
b11 \
b11 g
b0 %
b0 4
b0 f
b111 &
b111 3
b111 6
b111 [
1"
#110
0"
#120
b10000000 1
b10000000 :
17
b111 (
b111 5
b111 ]
b111 '
b111 \
b111 g
b100 %
b100 4
b100 f
b11 &
b11 3
b11 6
b11 [
1"
#130
0"
#140
b1000 1
b1000 :
07
b11 (
b11 5
b11 ]
b11 '
b11 \
b11 g
b0 %
b0 4
b0 f
b111 &
b111 3
b111 6
b111 [
1"
#150
0"
#160
b10000000 1
b10000000 :
17
b111 (
b111 5
b111 ]
b111 '
b111 \
b111 g
b100 %
b100 4
b100 f
b11 &
b11 3
b11 6
b11 [
1"
#170
0"
#180
b1000 1
b1000 :
07
b11 (
b11 5
b11 ]
b11 '
b11 \
b11 g
b0 %
b0 4
b0 f
b111 &
b111 3
b111 6
b111 [
1"
#190
0"
#200
b10000000 1
b10000000 :
17
b111 (
b111 5
b111 ]
b111 '
b111 \
b111 g
b100 %
b100 4
b100 f
b11 &
b11 3
b11 6
b11 [
1"
#210
0"
#220
b1000 1
b1000 :
07
b11 (
b11 5
b11 ]
b11 '
b11 \
b11 g
b1 %
b1 4
b1 f
b0 &
b0 3
b0 6
b0 [
1"
0#
#230
0"
#240
b100000 1
b100000 :
08
17
b101 (
b101 5
b101 ]
b101 '
b101 \
b101 g
b100 %
b100 4
b100 f
b11 &
b11 3
b11 6
b11 [
b101 ,
b101 I
b101 N
b101 b
b110 *
b110 Q
b110 V
b110 d
b101 +
b101 M
b101 R
b101 c
b101 -
b101 E
b101 J
b101 a
b10 .
b10 A
b10 F
b10 `
b1 /
b1 =
b1 B
b1 _
b0 0
b0 >
b0 W
b0 ^
1T
1P
0H
1D
1@
1<
1"
b11100111 $
1#
#250
0"
#260
b1000000 1
b1000000 :
09
18
b110 (
b110 5
b110 ]
b110 '
b110 \
b110 g
b110 %
b110 4
b110 f
b101 &
b101 3
b101 6
b101 [
1"
#270
0"
#280
b10000000 1
b10000000 :
19
b111 (
b111 5
b111 ]
b111 '
b111 \
b111 g
b111 %
b111 4
b111 f
b110 &
b110 3
b110 6
b110 [
1"
#290
0"
#300
b1 1
b1 :
09
08
07
b0 (
b0 5
b0 ]
b0 '
b0 \
b0 g
b0 %
b0 4
b0 f
b111 &
b111 3
b111 6
b111 [
1"
#310
0"
#320
b10 1
b10 :
19
b1 (
b1 5
b1 ]
b1 '
b1 \
b1 g
b1 %
b1 4
b1 f
b0 &
b0 3
b0 6
b0 [
1"
#330
0"
#340
b100 1
b100 :
09
18
b10 (
b10 5
b10 ]
b10 '
b10 \
b10 g
b10 %
b10 4
b10 f
b1 &
b1 3
b1 6
b1 [
1"
#350
0"
#360
b100000 1
b100000 :
19
08
17
b101 (
b101 5
b101 ]
b101 '
b101 \
b101 g
b11 %
b11 4
b11 f
b10 &
b10 3
b10 6
b10 [
1"
#370
0"
#380
b1000000 1
b1000000 :
09
18
b110 (
b110 5
b110 ]
b110 '
b110 \
b110 g
b110 %
b110 4
b110 f
b101 &
b101 3
b101 6
b101 [
1"
#390
0"
#400
b10000000 1
b10000000 :
19
b111 (
b111 5
b111 ]
b111 '
b111 \
b111 g
b111 %
b111 4
b111 f
b110 &
b110 3
b110 6
b110 [
1"
#410
0"
#420
b1 1
b1 :
09
08
07
b0 (
b0 5
b0 ]
b0 '
b0 \
b0 g
b0 %
b0 4
b0 f
b111 &
b111 3
b111 6
b111 [
1"
#430
0"
#440
b10 1
b10 :
19
b1 (
b1 5
b1 ]
b1 '
b1 \
b1 g
b1 %
b1 4
b1 f
b0 &
b0 3
b0 6
b0 [
1"
0#
#450
0"
#460
b1000 1
b1000 :
18
b11 (
b11 5
b11 ]
b11 '
b11 \
b11 g
b10 %
b10 4
b10 f
b1 &
b1 3
b1 6
b1 [
b11 ,
b11 I
b11 N
b11 b
b11 )
b11 U
b11 Z
b11 e
b11 *
b11 Q
b11 V
b11 d
b11 +
b11 M
b11 R
b11 c
b11 -
b11 E
b11 J
b11 a
b11 .
b11 A
b11 F
b11 `
b11 /
b11 =
b11 B
b11 _
b11 0
b11 >
b11 W
b11 ^
0Y
0T
0P
1H
0D
0@
0<
1"
b1000 $
1#
#470
0"
#480
b100 %
b100 4
b100 f
b11 &
b11 3
b11 6
b11 [
1"
#490
0"
#500
1"
#510
0"
#520
1"
#530
0"
#540
1"
#550
0"
#560
1"
#570
0"
#580
1"
#590
0"
#600
1"
#610
0"
#620
1"
#630
0"
#640
1"
#650
0"
#660
b1 %
b1 4
b1 f
b0 &
b0 3
b0 6
b0 [
1"
0#
#670
0"
#680
b100000 1
b100000 :
08
17
b101 (
b101 5
b101 ]
b101 '
b101 \
b101 g
b100 %
b100 4
b100 f
b11 &
b11 3
b11 6
b11 [
b101 .
b101 A
b101 F
b101 `
b1 *
b1 Q
b1 V
b1 d
b101 -
b101 E
b101 J
b101 a
b1 )
b1 U
b1 Z
b1 e
b101 ,
b101 I
b101 N
b101 b
b1 0
b1 >
b1 W
b1 ^
b101 +
b101 M
b101 R
b101 c
b1 /
b1 =
b1 B
b1 _
1P
0H
1@
1"
b100010 $
1#
#690
0"
#700
b10 1
b10 :
07
b1 (
b1 5
b1 ]
b1 '
b1 \
b1 g
b110 %
b110 4
b110 f
b101 &
b101 3
b101 6
b101 [
1"
#710
0"
#720
b100000 1
b100000 :
17
b101 (
b101 5
b101 ]
b101 '
b101 \
b101 g
b10 %
b10 4
b10 f
b1 &
b1 3
b1 6
b1 [
1"
#730
0"
#740
b10 1
b10 :
07
b1 (
b1 5
b1 ]
b1 '
b1 \
b1 g
b110 %
b110 4
b110 f
b101 &
b101 3
b101 6
b101 [
1"
#750
0"
#760
b100000 1
b100000 :
17
b101 (
b101 5
b101 ]
b101 '
b101 \
b101 g
b10 %
b10 4
b10 f
b1 &
b1 3
b1 6
b1 [
1"
#770
0"
#780
b10 1
b10 :
07
b1 (
b1 5
b1 ]
b1 '
b1 \
b1 g
b110 %
b110 4
b110 f
b101 &
b101 3
b101 6
b101 [
1"
#790
0"
#800
b100000 1
b100000 :
17
b101 (
b101 5
b101 ]
b101 '
b101 \
b101 g
b10 %
b10 4
b10 f
b1 &
b1 3
b1 6
b1 [
1"
#810
0"
#820
b10 1
b10 :
07
b1 (
b1 5
b1 ]
b1 '
b1 \
b1 g
b110 %
b110 4
b110 f
b101 &
b101 3
b101 6
b101 [
1"
#830
0"
#840
b100000 1
b100000 :
17
b101 (
b101 5
b101 ]
b101 '
b101 \
b101 g
b10 %
b10 4
b10 f
b1 &
b1 3
b1 6
b1 [
1"
#850
0"
#860
b10 1
b10 :
07
b1 (
b1 5
b1 ]
b1 '
b1 \
b1 g
b110 %
b110 4
b110 f
b101 &
b101 3
b101 6
b101 [
1"
#870
0"
#880
b100000 1
b100000 :
17
b101 (
b101 5
b101 ]
b101 '
b101 \
b101 g
b10 %
b10 4
b10 f
b1 &
b1 3
b1 6
b1 [
1"
#890
0"
#900
b10 1
b10 :
07
b1 (
b1 5
b1 ]
b1 '
b1 \
b1 g
b110 %
b110 4
b110 f
b101 &
b101 3
b101 6
b101 [
1"
#910
0"
#920
b100000 1
b100000 :
17
b101 (
b101 5
b101 ]
b101 '
b101 \
b101 g
b10 %
b10 4
b10 f
b1 &
b1 3
b1 6
b1 [
1"
#930
0"
#940
b10 1
b10 :
07
b1 (
b1 5
b1 ]
b1 '
b1 \
b1 g
b110 %
b110 4
b110 f
b101 &
b101 3
b101 6
b101 [
1"
#950
0"
#960
b100000 1
b100000 :
17
b101 (
b101 5
b101 ]
b101 '
b101 \
b101 g
b10 %
b10 4
b10 f
b1 &
b1 3
b1 6
b1 [
1"
#970
0"
#980
b10 1
b10 :
07
b1 (
b1 5
b1 ]
b1 '
b1 \
b1 g
b110 %
b110 4
b110 f
b101 &
b101 3
b101 6
b101 [
1"
#990
0"
#1000
b100000 1
b100000 :
17
b101 (
b101 5
b101 ]
b101 '
b101 \
b101 g
b10 %
b10 4
b10 f
b1 &
b1 3
b1 6
b1 [
1"
